ChangeLog
LICENSE
MANIFEST.in
README.md
README.rst
setup.py
bin/cacheBust
cachebust/__init__.py
cachebust.egg-info/PKG-INFO
cachebust.egg-info/SOURCES.txt
cachebust.egg-info/dependency_links.txt
cachebust.egg-info/requires.txt
cachebust.egg-info/top_level.txt
doc/cachebust.html
test/test.html
test/test.html~
test/z.sh
test/z.sh~
test/imgs/blah.gif
test/imgs/cheese1.gif
test/imgs/cheese10.gif
test/imgs/cheese11.gif
test/imgs/cheese12.gif
test/imgs/cheese13.gif
test/imgs/cheese14.gif
test/imgs/cheese15.gif
test/imgs/cheese16.gif
test/imgs/cheese17.gif
test/imgs/cheese18.gif
test/imgs/cheese19.gif
test/imgs/cheese2.gif
test/imgs/cheese20.gif
test/imgs/cheese21.gif
test/imgs/cheese22.gif
test/imgs/cheese23.gif
test/imgs/cheese24.gif
test/imgs/cheese25.gif
test/imgs/cheese26.gif
test/imgs/cheese27.gif
test/imgs/cheese28.gif
test/imgs/cheese29.gif
test/imgs/cheese3.gif
test/imgs/cheese30.gif
test/imgs/cheese31.gif
test/imgs/cheese32.gif
test/imgs/cheese33.gif
test/imgs/cheese34.gif
test/imgs/cheese35.gif
test/imgs/cheese36.gif
test/imgs/cheese37.gif
test/imgs/cheese38.gif
test/imgs/cheese39.gif
test/imgs/cheese4.gif
test/imgs/cheese40.gif
test/imgs/cheese41.gif
test/imgs/cheese42.gif
test/imgs/cheese43.gif
test/imgs/cheese44.gif
test/imgs/cheese45.gif
test/imgs/cheese46.gif
test/imgs/cheese47.gif
test/imgs/cheese48.gif
test/imgs/cheese49.gif
test/imgs/cheese5.gif
test/imgs/cheese50.gif
test/imgs/cheese6.gif
test/imgs/cheese7.gif
test/imgs/cheese8.gif
test/imgs/cheese9.gif
test/root/scripts/blah.js