Metadata-Version: 1.1
Name: cachebust
Version: 1.1.0
Summary: Provide a server-side means to ensure that clients always fetch assets when they are updated
Home-page: https://github.com/kata198/cachebust
Author: Tim Savannah
Author-email: kata198@gmail.com
License: LGPLv2
Keywords: cache,bust,url,md5,javascript,css,asset,update,cachebust,python,html
Platform: UNKNOWN
Classifier: Development Status :: 5 - Production/Stable
Classifier: Programming Language :: Python
Classifier: License :: OSI Approved :: GNU Lesser General Public License v2 (LGPLv2)
Classifier: Programming Language :: Python :: 2
Classifier: Programming Language :: Python :: 2
Classifier: Programming Language :: Python :: 2.7
Classifier: Programming Language :: Python :: 3
Classifier: Programming Language :: Python :: 3.3
Classifier: Programming Language :: Python :: 3.4
Classifier: Topic :: Internet :: WWW/HTTP
Classifier: Topic :: Text Processing :: Markup :: HTML
Classifier: Topic :: Software Development :: Libraries :: Python Modules
Requires: AdvancedHTMLParser
Requires: ArgumentParser
